barely_db/__init__.py
barely_db/configs.py
barely_db/examples.py
barely_db/file_management.py
barely_db/legacy.py
barely_db/parser.py
barely_db/tools.py
barely_db-0.8.1.dist-info/LICENSE
barely_db-0.8.1.dist-info/METADATA
barely_db-0.8.1.dist-info/WHEEL
barely_db-0.8.1.dist-info/top_level.txt
barely_db-0.8.1.dist-info/RECORD
