Metadata-Version: 2.1
Name: barely-db
Version: 0.8.1
Summary: A simple filesystem based database.
Home-page: https://bitbucket.org/battriondev/barely-db.git
Author: Deniz Bozyigit
Author-email: deniz195@gmail.com
License: MIT License
Requires-Dist: attrs
Requires-Dist: cattrs
